mfd_dmesg/__init__.py
mfd_dmesg/base.py
mfd_dmesg/constants.py
mfd_dmesg/enums.py
mfd_dmesg/exceptions.py
mfd_dmesg-1.20.0.dist-info/licenses/AUTHORS.md
mfd_dmesg-1.20.0.dist-info/licenses/LICENSE.md
mfd_dmesg-1.20.0.dist-info/METADATA
mfd_dmesg-1.20.0.dist-info/WHEEL
mfd_dmesg-1.20.0.dist-info/top_level.txt
mfd_dmesg-1.20.0.dist-info/RECORD
