Metadata-Version: 2.4
Name: mfd-dmesg
Version: 1.20.0
Summary: Modular Framework Design (MFD) module for diagnostic messages.
Project-URL: Homepage, https://github.com/intel/mfd
Project-URL: Repository, https://github.com/intel/mfd-dmesg
Project-URL: Issues, https://github.com/intel/mfd-dmesg/issues
Project-URL: Changelog, https://github.com/intel/mfd-dmesg/blob/main/CHANGELOG.md
Requires-Python: <3.14,>=3.10
License-File: LICENSE.md
License-File: AUTHORS.md
Requires-Dist: mfd-common-libs<2,>=1.11.0
Requires-Dist: mfd-base-tool<3,>=2.7.0
Requires-Dist: mfd-typing<2,>=1.23.0
Dynamic: license-file
